{
	"dataset": {
		"dataset.id": 220079,
		"dataset.name": "01_sou_044016_220079_wear_02top_01blouse_woman",
		"dataset.image_path": "./008.의류 통합 데이터(3-1)/원천데이터/상품/상의/blouse/01_sou_044016_220079_wear_02top_01blouse_woman.jpg",
		"dataset.label_path": "./008.의류 통합 데이터(3-1)/라벨링데이터/상품/상의/blouse/01_sou_044016_220079_wear_02top_01blouse_woman.json",
		"dataset.category": 5,
		"dataset.type": 1,
		"dataset.width": 2268,
		"dataset.height": 4032,
		"dataset.file_size": 730771
	},
	"annotation": [
		{
			"annotation_type": "Polygon",
			"annotation_id": 146,
			"annotation_point_count": 75.0,
			"annotation_point": [
				614.0,
				1070.0,
				544.0,
				1141.0,
				521.0,
				1180.0,
				578.0,
				1289.0,
				644.0,
				1355.0,
				631.0,
				1546.0,
				658.0,
				1667.0,
				681.0,
				1722.0,
				708.0,
				1835.0,
				704.0,
				1901.0,
				684.0,
				1952.0,
				676.935546875,
				2130.708984375,
				676.935546875,
				2130.708984375,
				693.6554096310247,
				2138.3083176985674,
				716.4561184073427,
				2144.3885067055853,
				740.776874435418,
				2155.0288374678676,
				765.09765625,
				2158.068359375,
				765.09765625,
				2158.068359375,
				784.8582447363005,
				2153.508790216114,
				809.1790007643722,
				2151.9887429643604,
				828.9396150371831,
				2155.0288374678676,
				853.2603710652547,
				2158.0689319713783,
				879.1011743450836,
				2158.0689319713783,
				903.4219303731552,
				2158.0689319713783,
				926.2226391494733,
				2158.0689319713783,
				947.5033006740377,
				2159.588979223132,
				971.824056702113,
				2159.588979223132,
				999.1849072336954,
				2159.588979223132,
				1111.6684038635321,
				2155.0288374678676,
				1134.4691126398502,
				2147.428601209096,
				1146.629490653886,
				2142.8684594538317,
				1244.0,
				2139.0,
				1308.0,
				2127.0,
				1318.0,
				2096.0,
				1318.0,
				2065.0,
				1304.0,
				2030.0,
				1288.0,
				1940.0,
				1291.0,
				1815.0,
				1258.0,
				1675.0,
				1284.0,
				1480.0,
				1279.287054409011,
				1401.4258911819961,
				1270.5315822389057,
				1348.8930581613567,
				1283.6647904940655,
				1337.948717948726,
				1309.9312070043852,
				1309.4934333958809,
				1331.8198874296504,
				1285.4158849280866,
				1351.5196998123902,
				1256.9606003752415,
				1377.7861163227099,
				1232.8830519074472,
				1388.7304565353406,
				1204.427767354602,
				1382.1640625,
				1208.8046875,
				1382.1640625,
				1208.8046875,
				1391.0,
				1176.0,
				1421.0,
				1129.0,
				1294.0,
				1039.0,
				1183.110624695997,
				1004.3530678896605,
				1148.1495379056432,
				986.1125008686031,
				1142.0693488986217,
				989.1525953721139,
				1119.2686401223036,
				998.2728788826425,
				1099.5080258494963,
				1007.3931623931676,
				1076.7073170731783,
				1011.9533041484319,
				1052.386561045103,
				1016.5134459036963,
				1029.585852268785,
				1021.0735876589606,
				1005.2650962407133,
				1024.1136821624677,
				979.4242929608845,
				1024.1136821624677,
				955.1035369328129,
				1024.1136821624677,
				929.262733652984,
				1024.1136821624677,
				903.4219303731552,
				1022.5936349107142,
				880.6212215968371,
				1019.5535404072034,
				857.8205128205191,
				1016.5134459036963,
				833.4997567924438,
				1011.9533041484319,
				807.6589535126186,
				1007.3931623931676,
				789.4183864915613,
				1002.8330206379032,
				769.658203125,
				993.712890625,
				769.658203125,
				993.712890625,
				718.0,
				1020.0,
				671.0,
				1031.0
			]
		}
	],
	"metadata.model": {
		"metadata.model.gender": "FEMALE",
		"metadata.model.age": "30대",
		"metadata.model.job": "entertainment and sports",
		"metadata.model.type": "wear",
		"metadata.model.usually_size": "M",
		"metadata.model.body_height": "172",
		"metadata.model.waist_height": "106",
		"metadata.model.chest_size_male": "null",
		"metadata.model.breast_size_female": "83.0",
		"metadata.model.waist_size": "71",
		"metadata.model.hip_seize": "90",
		"metadata.model.back_length": "42",
		"metadata.model.shoulders_width": "41",
		"metadata.model.arm_length": "58",
		"metadata.model.weight": "53"
	},
	"metadata.clothes": {
		"metadata.clothes.type": "02top_01blouse",
		"metadata.clothes.season": "summer",
		"metadata.clothes.fiber_composition": "Polyester",
		"metadata.clothes.elasticity": "none",
		"metadata.clothes.transparency": "contain",
		"metadata.clothes.isfleece": "fleece_none",
		"metadata.clothes.color": "White",
		"metadata.clothes.washing_method": "none",
		"metadata.clothes.bleach": "none",
		"metadata.clothes.ironing": "none",
		"metadata.clothes.drycleaning": "none",
		"metadata.clothes.wringing": "none",
		"metadata.clothes.drying": "none",
		"metadata.clothes.top_length_type": "normal",
		"metadata.clothes.sleeve_length_type": "sleeveless",
		"metadata.clothes.topneck_color_design": "U-neck",
		"metadata.clothes.topsleeve_design": "null",
		"metadata.clothes.pants_silhouette": "null",
		"metadata.clothes.skirt_design": "null",
		"metadata.top.front_length": "63.0",
		"metadata.top.chest_size": "106.0",
		"metadata.top.waist_size": "106.0",
		"metadata.top.hem_size": "104.0",
		"metadata.top.shoulder_width": "52.0",
		"metadata.top.sleeve_length": "0.0",
		"metadata.top.sleeve_cuff_size": "0.0",
		"metadata.pants.pants_length": "null",
		"metadata.pants.waist_size": "null",
		"metadata.pants.hip_size": "null",
		"metadata.pants.front_rise_length": "null",
		"metadata.pants.back_rise_length": "null",
		"metadata.pants.inner_seam_length": "null",
		"metadata.pants.pants_waist_size": "null",
		"metadata.skirt.length": "null",
		"metadata.skirt.waist_size": "null",
		"metadata.skirt.hip_size": "null",
		"metadata.skirt.hem_size": "null",
		"metadata.dress.front_length": "null",
		"metadata.dress.chest_size": "null",
		"metadata.dress.waist_size": "null",
		"metadata.dress.hip_size": "null",
		"metadata.dress.hem_size": "null",
		"metadata.dress.shoulder_width": "null",
		"metadata.dress.sleeve_length": "null",
		"metadata.dress.cuff_size": "null",
		"metadata.jumpsuit.front_length": "null",
		"metadata.jumpsuit.inner_seam_length": "null",
		"metadata.jumpsuit.chest_size": "null",
		"metadata.jumpsuit.waist_size": "null",
		"metadata.jumpsuit.hip_size": "null",
		"metadata.jumpsuit.shoulder_width": "null",
		"metadata.jumpsuit.sleeve_length": "null",
		"metadata.jumpsuit.cuffs_size": "null",
		"metadata.jumpsuit.front_rise_length": "null",
		"metadata.jumpsuit.back_rise_length": "null",
		"metadata.jumpsuit.pants_waist_size": "null"
	}
}