{
	"dataset": {
		"dataset.id": 21187,
		"dataset.name": "01_sou_004238_021187_back_02top_01blouse_woman",
		"dataset.image_path": "./008.의류 통합 데이터(3-1)/원천데이터/상품/상의/blouse/01_sou_004238_021187_back_02top_01blouse_woman.jpg",
		"dataset.label_path": "./008.의류 통합 데이터(3-1)/라벨링데이터/상품/상의/blouse/01_sou_004238_021187_back_02top_01blouse_woman.json",
		"dataset.category": 5,
		"dataset.type": 1,
		"dataset.width": 1080,
		"dataset.height": 1080,
		"dataset.file_size": 47315
	},
	"annotation": [
		{
			"annotation_type": "Polygon",
			"annotation_id": 287,
			"annotation_point_count": 83.0,
			"annotation_point": [
				597.0,
				103.0,
				573.0,
				109.0,
				529.0,
				137.0,
				479.0,
				133.0,
				465.0,
				124.0,
				405.0,
				109.0,
				351.0,
				137.0,
				289.7999999999993,
				159.10000000000218,
				253.0,
				180.0,
				206.70000000000073,
				241.20000000000073,
				84.90000000000146,
				340.2000000000007,
				57.0,
				376.0,
				0.0,
				389.0,
				3.0,
				432.0,
				16.0,
				447.0,
				37.0,
				456.0,
				57.0,
				475.0,
				81.0,
				515.0,
				100.10000000000218,
				533.1000000000022,
				140.5,
				502.1000000000022,
				151.0,
				481.0,
				172.0,
				481.0,
				158.0,
				558.0,
				155.0,
				619.0,
				128.0,
				727.0,
				121.0,
				841.0,
				128.0,
				850.0,
				168.0,
				862.0,
				246.0,
				942.0,
				300.0,
				982.0,
				326.884765625,
				993.92578125,
				331.47945406909275,
				996.8494679713476,
				385.78514330019243,
				1013.1411747406783,
				444.2681932413725,
				1026.5087290129486,
				522.3848385199526,
				1027.3442011549669,
				602.1724280825656,
				1024.0023125868975,
				668.5924633729119,
				1013.9766468826965,
				702.0113490535878,
				1005.6219254625285,
				716.2143754678727,
				994.3430515453001,
				766.0,
				970.0,
				813.0,
				930.0,
				860.0,
				853.0,
				897.0,
				819.0,
				880.0,
				668.0,
				850.0,
				549.0,
				837.0,
				450.0,
				840.0,
				447.0,
				853.0,
				462.0,
				884.0,
				478.0,
				928.0,
				521.0,
				938.0,
				521.0,
				945.0,
				515.0,
				944.4000000000015,
				490.40000000000146,
				999.1000000000022,
				425.2999999999993,
				1017.4000000000015,
				401.0,
				1024.9000000000015,
				376.0,
				1012.0,
				367.0,
				955.0,
				346.0,
				914.0,
				303.0,
				832.6049278746323,
				259.9293877511773,
				814.6190692617711,
				236.72182825070558,
				812.2983133117232,
				232.95059983188185,
				810.2676518554326,
				228.30908793178605,
				807.3667069178737,
				223.9576705254476,
				804.4947714296904,
				219.31615862535546,
				800.6945335614873,
				215.25483571277073,
				797.5034941301747,
				212.06379628145805,
				793.4711806669657,
				208.29256786263068,
				789.3808483050088,
				204.81143393756065,
				785.3195253924277,
				200.1699220374685,
				782.7086749486225,
				197.55907159366325,
				779.5176355173098,
				194.94822114986164,
				775.7464070984825,
				192.04727621230268,
				770.5247062108792,
				187.11566981845317,
				768.8131486977181,
				183.92463038713686,
				766.7534777920519,
				180.15340196831312,
				763.3013533163576,
				177.25245703075416,
				759.7912099419118,
				173.48122861192678,
				756.0489909724602,
				170.58028367436782,
				751.958984375,
				170.0,
				678.0,
				133.0,
				634.1000000000022,
				132.10000000000218,
				644.5,
				119.60000000000218
			]
		}
	],
	"metadata.model": {
		"metadata.model.gender": "FEMALE",
		"metadata.model.age": "40대",
		"metadata.model.job": "homemaker",
		"metadata.model.type": "back",
		"metadata.model.usually_size": "L",
		"metadata.model.body_height": "160",
		"metadata.model.waist_height": "94",
		"metadata.model.chest_size_male": "null",
		"metadata.model.breast_size_female": "89.0",
		"metadata.model.waist_size": "94",
		"metadata.model.hip_seize": "105",
		"metadata.model.back_length": "39",
		"metadata.model.shoulders_width": "41",
		"metadata.model.arm_length": "52",
		"metadata.model.weight": "70"
	},
	"metadata.clothes": {
		"metadata.clothes.type": "02top_01blouse",
		"metadata.clothes.season": "summer",
		"metadata.clothes.fiber_composition": "Cotton,Polyester",
		"metadata.clothes.elasticity": "none at all",
		"metadata.clothes.transparency": "none",
		"metadata.clothes.isfleece": "fleece_none",
		"metadata.clothes.color": "White",
		"metadata.clothes.washing_method": "none",
		"metadata.clothes.bleach": "none",
		"metadata.clothes.ironing": "none",
		"metadata.clothes.drycleaning": "none",
		"metadata.clothes.wringing": "none",
		"metadata.clothes.drying": "none",
		"metadata.clothes.top_length_type": "long",
		"metadata.clothes.sleeve_length_type": "short sleeves",
		"metadata.clothes.topneck_color_design": "Peter Pan collar",
		"metadata.clothes.topsleeve_design": "cape sleeve",
		"metadata.clothes.pants_silhouette": "null",
		"metadata.clothes.skirt_design": "null",
		"metadata.top.front_length": "65.0",
		"metadata.top.chest_size": "98.0",
		"metadata.top.waist_size": "110.0",
		"metadata.top.hem_size": "112.0",
		"metadata.top.shoulder_width": "38.0",
		"metadata.top.sleeve_length": "29.0",
		"metadata.top.sleeve_cuff_size": "36.0",
		"metadata.pants.pants_length": "null",
		"metadata.pants.waist_size": "null",
		"metadata.pants.hip_size": "null",
		"metadata.pants.front_rise_length": "null",
		"metadata.pants.back_rise_length": "null",
		"metadata.pants.inner_seam_length": "null",
		"metadata.pants.pants_waist_size": "null",
		"metadata.skirt.length": "null",
		"metadata.skirt.waist_size": "null",
		"metadata.skirt.hip_size": "null",
		"metadata.skirt.hem_size": "null",
		"metadata.dress.front_length": "null",
		"metadata.dress.chest_size": "null",
		"metadata.dress.waist_size": "null",
		"metadata.dress.hip_size": "null",
		"metadata.dress.hem_size": "null",
		"metadata.dress.shoulder_width": "null",
		"metadata.dress.sleeve_length": "null",
		"metadata.dress.cuff_size": "null",
		"metadata.jumpsuit.front_length": "null",
		"metadata.jumpsuit.inner_seam_length": "null",
		"metadata.jumpsuit.chest_size": "null",
		"metadata.jumpsuit.waist_size": "null",
		"metadata.jumpsuit.hip_size": "null",
		"metadata.jumpsuit.shoulder_width": "null",
		"metadata.jumpsuit.sleeve_length": "null",
		"metadata.jumpsuit.cuffs_size": "null",
		"metadata.jumpsuit.front_rise_length": "null",
		"metadata.jumpsuit.back_rise_length": "null",
		"metadata.jumpsuit.pants_waist_size": "null"
	}
}