{
	"dataset": {
		"dataset.id": 220593,
		"dataset.name": "01_sou_044119_220593_wear_02top_01blouse_woman",
		"dataset.image_path": "./008.의류 통합 데이터(3-1)/원천데이터/상품/상의/blouse/01_sou_044119_220593_wear_02top_01blouse_woman.jpg",
		"dataset.label_path": "./008.의류 통합 데이터(3-1)/라벨링데이터/상품/상의/blouse/01_sou_044119_220593_wear_02top_01blouse_woman.json",
		"dataset.category": 5,
		"dataset.type": 1,
		"dataset.width": 1816,
		"dataset.height": 4032,
		"dataset.file_size": 693269
	},
	"annotation": [
		{
			"annotation_type": "Polygon",
			"annotation_id": 60,
			"annotation_point_count": 71.0,
			"annotation_point": [
				913.0,
				2019.0,
				865.0,
				2049.0,
				831.0,
				2089.0,
				777.0,
				2184.0,
				755.0,
				2254.0,
				730.0,
				2304.0,
				683.0,
				2448.0,
				683.0,
				2470.0,
				671.0,
				2483.0,
				670.279296875,
				2521.294921875,
				670.279296875,
				2521.294921875,
				681.0005882988044,
				2527.068984784153,
				693.3714898120634,
				2534.4915256921086,
				704.0929377902248,
				2542.7387933676146,
				714.8143857683826,
				2550.9860610431206,
				727.1852872816416,
				2560.882782253728,
				742.0303690975525,
				2555.1096948808736,
				768.0,
				2522.0,
				803.0,
				2498.0,
				862.0,
				2409.0,
				865.0,
				2465.0,
				853.0,
				2529.0,
				850.0,
				2631.0,
				869.0,
				2666.0,
				1012.8000000000029,
				2672.0,
				1239.0,
				2672.0,
				1274.0,
				2668.0,
				1286.0,
				2637.0,
				1283.0,
				2561.0,
				1274.0,
				2542.0,
				1267.0,
				2420.0,
				1274.0,
				2415.0,
				1293.0,
				2459.0,
				1315.0,
				2489.0,
				1352.0,
				2522.0,
				1387.0,
				2539.0,
				1409.0,
				2568.0,
				1418.0,
				2563.0,
				1431.501953125,
				2563.357421875,
				1440.5739412129442,
				2560.058055486177,
				1452.9448427262032,
				2552.635514578222,
				1462.8415639368104,
				2545.2129736702664,
				1479.3360992878224,
				2532.8420721570074,
				1476.03719221762,
				2503.1519085251857,
				1459.0,
				2481.0,
				1456.0,
				2450.0,
				1406.0,
				2291.0,
				1355.0,
				2180.0,
				1315.0,
				2137.0,
				1280.0,
				2065.0,
				1230.0,
				2025.0,
				1164.2904740834783,
				1997.5944000166455,
				1155.2184796404217,
				2015.7383889027587,
				1152.74429933777,
				2019.8620227405117,
				1142.022851359612,
				2027.2845636484672,
				1130.4766766139037,
				2032.2329242537708,
				1117.281048333094,
				2035.5318313239732,
				1102.4359665171833,
				2037.1812848590744,
				1092.5392453065724,
				2039.6554651617262,
				1078.5188902582122,
				2042.9543722319286,
				1064.498535209852,
				2042.9543722319286,
				1051.3029069290424,
				2042.9543722319286,
				1031.509464507828,
				2039.6554651617262,
				1024.9116503674231,
				2039.6554651617262,
				1011.7160220866099,
				2039.6554651617262,
				998.5203938058003,
				2036.3565580915238,
				985.3247655249907,
				2031.4081974862202,
				973.7785907792822,
				2027.2845636484672,
				962.2324160335738,
				2015.7383889027587,
				958.109375,
				2004.19140625,
				958.109375,
				2004.19140625
			]
		}
	],
	"metadata.model": {
		"metadata.model.gender": "FEMALE",
		"metadata.model.age": "40대",
		"metadata.model.job": "homemaker",
		"metadata.model.type": "wear",
		"metadata.model.usually_size": "S",
		"metadata.model.body_height": "163",
		"metadata.model.waist_height": "95",
		"metadata.model.chest_size_male": "null",
		"metadata.model.breast_size_female": "79.0",
		"metadata.model.waist_size": "73",
		"metadata.model.hip_seize": "87",
		"metadata.model.back_length": "41",
		"metadata.model.shoulders_width": "42",
		"metadata.model.arm_length": "53",
		"metadata.model.weight": "50"
	},
	"metadata.clothes": {
		"metadata.clothes.type": "02top_01blouse",
		"metadata.clothes.season": "summer",
		"metadata.clothes.fiber_composition": "synthetic fiber Others",
		"metadata.clothes.elasticity": "none at all",
		"metadata.clothes.transparency": "contain a lot",
		"metadata.clothes.isfleece": "fleece_none",
		"metadata.clothes.color": "Brown",
		"metadata.clothes.washing_method": "none",
		"metadata.clothes.bleach": "none",
		"metadata.clothes.ironing": "none",
		"metadata.clothes.drycleaning": "none",
		"metadata.clothes.wringing": "none",
		"metadata.clothes.drying": "none",
		"metadata.clothes.top_length_type": "normal",
		"metadata.clothes.sleeve_length_type": "long sleeves",
		"metadata.clothes.topneck_color_design": "round neck",
		"metadata.clothes.topsleeve_design": "puff sleeve",
		"metadata.clothes.pants_silhouette": "null",
		"metadata.clothes.skirt_design": "null",
		"metadata.top.front_length": "58.0",
		"metadata.top.chest_size": "102.0",
		"metadata.top.waist_size": "104.0",
		"metadata.top.hem_size": "106.0",
		"metadata.top.shoulder_width": "50.0",
		"metadata.top.sleeve_length": "34.0",
		"metadata.top.sleeve_cuff_size": "24.0",
		"metadata.pants.pants_length": "null",
		"metadata.pants.waist_size": "null",
		"metadata.pants.hip_size": "null",
		"metadata.pants.front_rise_length": "null",
		"metadata.pants.back_rise_length": "null",
		"metadata.pants.inner_seam_length": "null",
		"metadata.pants.pants_waist_size": "null",
		"metadata.skirt.length": "null",
		"metadata.skirt.waist_size": "null",
		"metadata.skirt.hip_size": "null",
		"metadata.skirt.hem_size": "null",
		"metadata.dress.front_length": "null",
		"metadata.dress.chest_size": "null",
		"metadata.dress.waist_size": "null",
		"metadata.dress.hip_size": "null",
		"metadata.dress.hem_size": "null",
		"metadata.dress.shoulder_width": "null",
		"metadata.dress.sleeve_length": "null",
		"metadata.dress.cuff_size": "null",
		"metadata.jumpsuit.front_length": "null",
		"metadata.jumpsuit.inner_seam_length": "null",
		"metadata.jumpsuit.chest_size": "null",
		"metadata.jumpsuit.waist_size": "null",
		"metadata.jumpsuit.hip_size": "null",
		"metadata.jumpsuit.shoulder_width": "null",
		"metadata.jumpsuit.sleeve_length": "null",
		"metadata.jumpsuit.cuffs_size": "null",
		"metadata.jumpsuit.front_rise_length": "null",
		"metadata.jumpsuit.back_rise_length": "null",
		"metadata.jumpsuit.pants_waist_size": "null"
	}
}