{
	"dataset": {
		"dataset.id": 49101,
		"dataset.name": "01_sou_009821_049101_front_02top_02t-shirt_man",
		"dataset.image_path": "./008.의류 통합 데이터(3-1)/원천데이터/상품/상의/t-shirt/01_sou_009821_049101_front_02top_02t-shirt_man.jpg",
		"dataset.label_path": "./008.의류 통합 데이터(3-1)/라벨링데이터/상품/상의/t-shirt/01_sou_009821_049101_front_02top_02t-shirt_man.json",
		"dataset.category": 6,
		"dataset.type": 1,
		"dataset.width": 1440,
		"dataset.height": 1080,
		"dataset.file_size": 228754
	},
	"annotation": [
		{
			"annotation_type": "Polygon",
			"annotation_id": 16,
			"annotation_point_count": 51.0,
			"annotation_point": [
				493.0,
				557.3000000000011,
				493.0,
				840.0,
				487.40000000000146,
				881.3000000000011,
				579.4000000000015,
				882.7000000000007,
				722.1000000000004,
				876.7000000000007,
				917.9000000000015,
				873.1000000000004,
				942.7000000000007,
				870.3000000000011,
				940.9000000000015,
				846.0,
				937.7000000000007,
				787.1000000000004,
				931.0,
				560.5,
				915.2000000000007,
				497.60000000000036,
				998.6763848396513,
				532.1982507288631,
				1099.4344023323629,
				568.4081632653069,
				1190.7463556851326,
				601.4693877551035,
				1255.2944606414003,
				625.0845481049564,
				1288.3556851311969,
				640.8279883381929,
				1308.8221574344025,
				651.8483965014584,
				1326.1399416909626,
				629.8075801749274,
				1346.60641399417,
				604.6180758017508,
				1318.2682215743444,
				568.4081632653069,
				1269.4635568513131,
				522.7521865889212,
				1182.8746355685143,
				467.65014577259535,
				1105.7317784256575,
				425.1428571428587,
				1045.9067055393589,
				388.9329446064148,
				979.7842565597675,
				349.57434402332365,
				923.107871720118,
				316.5131195335289,
				902.6413994169106,
				303.9183673469397,
				844.3906705539375,
				283.4518950437323,
				798.7346938775518,
				278.72886297376135,
				779.842565597668,
				248.81632653061388,
				646.0233236151616,
				248.81632653061388,
				630.3000000000011,
				277.2000000000007,
				562.6000000000004,
				289.7000000000007,
				527.9000000000015,
				299.2000000000007,
				494.88629737609335,
				314.93877551020523,
				444.50728862973847,
				346.42565597667635,
				321.7084548104958,
				421.9941690962114,
				228.82215743440247,
				478.6705539358609,
				145.381924198251,
				529.0495626822158,
				101.3002915451907,
				566.8338192419833,
				65.09037900874682,
				595.1720116618089,
				93.42857142857247,
				620.3615160349855,
				115.46938775510353,
				654.9970845481057,
				156.39999999999964,
				629.8000000000011,
				194.18658892128406,
				617.2128279883382,
				283.9241982507301,
				582.5772594752198,
				331.1545189504377,
				568.4081632653069,
				400.42565597667635,
				544.7930029154522,
				460.25072886297494,
				522.7521865889212,
				498.03498542274065,
				486.5422740524791,
				496.460641399417,
				535.3469387755104
			]
		}
	],
	"metadata.model": {
		"metadata.model.gender": "MALE",
		"metadata.model.age": "40대",
		"metadata.model.job": "office job",
		"metadata.model.type": "front",
		"metadata.model.usually_size": "L",
		"metadata.model.body_height": "173",
		"metadata.model.waist_height": "102",
		"metadata.model.chest_size_male": "89.0",
		"metadata.model.breast_size_female": "null",
		"metadata.model.waist_size": "85",
		"metadata.model.hip_seize": "94",
		"metadata.model.back_length": "42",
		"metadata.model.shoulders_width": "40",
		"metadata.model.arm_length": "56",
		"metadata.model.weight": "64"
	},
	"metadata.clothes": {
		"metadata.clothes.type": "02top_02t-shirt",
		"metadata.clothes.season": "spring&fall",
		"metadata.clothes.fiber_composition": "Polyester",
		"metadata.clothes.elasticity": "contain little",
		"metadata.clothes.transparency": "none at all",
		"metadata.clothes.isfleece": "fleece_none",
		"metadata.clothes.color": "Blue,Orange,Gray",
		"metadata.clothes.washing_method": "Washing30",
		"metadata.clothes.bleach": "Do not chlorine bleach",
		"metadata.clothes.ironing": "Ironing 80~120℃ : Place a cloth between the iron and textile",
		"metadata.clothes.drycleaning": "none",
		"metadata.clothes.wringing": "Do not wringing",
		"metadata.clothes.drying": "Drip dry in shade",
		"metadata.clothes.top_length_type": "normal",
		"metadata.clothes.sleeve_length_type": "long sleeves",
		"metadata.clothes.topneck_color_design": "polo collar",
		"metadata.clothes.topsleeve_design": "ribbed sleeve",
		"metadata.clothes.pants_silhouette": "null",
		"metadata.clothes.skirt_design": "null",
		"metadata.top.front_length": "69.0",
		"metadata.top.chest_size": "96.0",
		"metadata.top.waist_size": "96.0",
		"metadata.top.hem_size": "96.0",
		"metadata.top.shoulder_width": "43.0",
		"metadata.top.sleeve_length": "60.0",
		"metadata.top.sleeve_cuff_size": "16.0",
		"metadata.pants.pants_length": "null",
		"metadata.pants.waist_size": "null",
		"metadata.pants.hip_size": "null",
		"metadata.pants.front_rise_length": "null",
		"metadata.pants.back_rise_length": "null",
		"metadata.pants.inner_seam_length": "null",
		"metadata.pants.pants_waist_size": "null",
		"metadata.skirt.length": "null",
		"metadata.skirt.waist_size": "null",
		"metadata.skirt.hip_size": "null",
		"metadata.skirt.hem_size": "null",
		"metadata.dress.front_length": "null",
		"metadata.dress.chest_size": "null",
		"metadata.dress.waist_size": "null",
		"metadata.dress.hip_size": "null",
		"metadata.dress.hem_size": "null",
		"metadata.dress.shoulder_width": "null",
		"metadata.dress.sleeve_length": "null",
		"metadata.dress.cuff_size": "null",
		"metadata.jumpsuit.front_length": "null",
		"metadata.jumpsuit.inner_seam_length": "null",
		"metadata.jumpsuit.chest_size": "null",
		"metadata.jumpsuit.waist_size": "null",
		"metadata.jumpsuit.hip_size": "null",
		"metadata.jumpsuit.shoulder_width": "null",
		"metadata.jumpsuit.sleeve_length": "null",
		"metadata.jumpsuit.cuffs_size": "null",
		"metadata.jumpsuit.front_rise_length": "null",
		"metadata.jumpsuit.back_rise_length": "null",
		"metadata.jumpsuit.pants_waist_size": "null"
	}
}