{
	"dataset": {
		"dataset.id": 10938,
		"dataset.name": "01_sou_002188_010938_wear_02top_02t-shirt_man",
		"dataset.image_path": "./008.의류 통합 데이터(3-1)/원천데이터/상품/상의/t-shirt/01_sou_002188_010938_wear_02top_02t-shirt_man.jpg",
		"dataset.label_path": "./008.의류 통합 데이터(3-1)/라벨링데이터/상품/상의/t-shirt/01_sou_002188_010938_wear_02top_02t-shirt_man.json",
		"dataset.category": 6,
		"dataset.type": 1,
		"dataset.width": 810,
		"dataset.height": 1080,
		"dataset.file_size": 60740
	},
	"annotation": [
		{
			"annotation_type": "Polygon",
			"annotation_id": 403,
			"annotation_point_count": 64.0,
			"annotation_point": [
				343.0,
				305.0,
				327.0,
				331.0,
				319.0,
				376.0,
				312.0,
				389.0,
				313.0,
				392.0,
				311.0,
				393.0,
				307.0,
				410.0,
				301.0,
				422.0,
				302.0,
				427.0,
				293.0,
				449.0,
				276.73828125,
				512.849609375,
				274.1666666666606,
				517.9938271604879,
				271.08024691357423,
				540.6275720164558,
				301.944444444438,
				542.6851851851789,
				317.37654320986985,
				501.0185185185146,
				322.5205761316829,
				486.10082304526077,
				341.0,
				446.0,
				357.7000000000007,
				410.2000000000007,
				352.0,
				456.0,
				347.0,
				493.0,
				349.0,
				517.0,
				347.0,
				524.0,
				348.0,
				534.0,
				343.09765625,
				546.80078125,
				354.41358024691,
				542.1707818929972,
				406.88271604937836,
				529.3106995884737,
				435.1748971193374,
				529.8251028806517,
				471.69753086419223,
				530.3395061728334,
				512.3353909464968,
				531.3683127571967,
				520.0514403292145,
				536.5123456790061,
				522.0,
				534.0,
				515.0,
				520.0,
				512.0,
				482.0,
				506.0,
				456.0,
				509.0,
				436.0,
				513.0,
				434.0,
				528.0,
				450.0,
				550.0,
				490.0,
				565.0,
				508.0,
				567.0,
				516.0,
				576.63671875,
				534.96875,
				590.5246913580195,
				528.2818930041103,
				605.9567901234514,
				528.2818930041103,
				600.812757201642,
				517.4794238683062,
				595.0,
				496.0,
				589.0,
				489.0,
				586.0,
				469.0,
				567.0,
				425.0,
				565.0,
				411.0,
				558.0,
				405.0,
				558.0,
				398.0,
				549.0,
				382.0,
				537.0,
				345.0,
				534.0,
				326.0,
				519.0,
				301.0,
				505.0,
				293.0,
				465.5246913580195,
				283.4259259259197,
				461.92386831275144,
				262.84979423867844,
				431.060546875,
				280.853515625,
				423.34362139916993,
				281.3683127571967,
				397.62345679011923,
				271.08024691357423,
				390.935546875,
				285.998046875,
				381.0,
				292.0,
				358.0,
				297.0
			]
		}
	],
	"metadata.model": {
		"metadata.model.gender": "MALE",
		"metadata.model.age": "40대",
		"metadata.model.job": "Others",
		"metadata.model.type": "wear",
		"metadata.model.usually_size": "L",
		"metadata.model.body_height": "170",
		"metadata.model.waist_height": "91",
		"metadata.model.chest_size_male": "90.0",
		"metadata.model.breast_size_female": "null",
		"metadata.model.waist_size": "80",
		"metadata.model.hip_seize": "98",
		"metadata.model.back_length": "48",
		"metadata.model.shoulders_width": "40",
		"metadata.model.arm_length": "55",
		"metadata.model.weight": "70"
	},
	"metadata.clothes": {
		"metadata.clothes.type": "02top_02t-shirt",
		"metadata.clothes.season": "winter",
		"metadata.clothes.fiber_composition": "Cotton",
		"metadata.clothes.elasticity": "contain little",
		"metadata.clothes.transparency": "none at all",
		"metadata.clothes.isfleece": "fleece_none",
		"metadata.clothes.color": "Gray",
		"metadata.clothes.washing_method": "Washing40_1",
		"metadata.clothes.bleach": "Do not chlorine bleach",
		"metadata.clothes.ironing": "Ironing 180~210℃ : Place a cloth between the iron and textile",
		"metadata.clothes.drycleaning": "DRYCLEAN : petroleum solvent only",
		"metadata.clothes.wringing": "Do not wringing",
		"metadata.clothes.drying": "Line dry in shade",
		"metadata.clothes.top_length_type": "normal",
		"metadata.clothes.sleeve_length_type": "long sleeves",
		"metadata.clothes.topneck_color_design": "polo collar",
		"metadata.clothes.topsleeve_design": "ribbed sleeve",
		"metadata.clothes.pants_silhouette": "null",
		"metadata.clothes.skirt_design": "null",
		"metadata.top.front_length": "69.0",
		"metadata.top.chest_size": "102.0",
		"metadata.top.waist_size": "102.0",
		"metadata.top.hem_size": "100.0",
		"metadata.top.shoulder_width": "49.0",
		"metadata.top.sleeve_length": "61.0",
		"metadata.top.sleeve_cuff_size": "22.0",
		"metadata.pants.pants_length": "null",
		"metadata.pants.waist_size": "null",
		"metadata.pants.hip_size": "null",
		"metadata.pants.front_rise_length": "null",
		"metadata.pants.back_rise_length": "null",
		"metadata.pants.inner_seam_length": "null",
		"metadata.pants.pants_waist_size": "null",
		"metadata.skirt.length": "null",
		"metadata.skirt.waist_size": "null",
		"metadata.skirt.hip_size": "null",
		"metadata.skirt.hem_size": "null",
		"metadata.dress.front_length": "null",
		"metadata.dress.chest_size": "null",
		"metadata.dress.waist_size": "null",
		"metadata.dress.hip_size": "null",
		"metadata.dress.hem_size": "null",
		"metadata.dress.shoulder_width": "null",
		"metadata.dress.sleeve_length": "null",
		"metadata.dress.cuff_size": "null",
		"metadata.jumpsuit.front_length": "null",
		"metadata.jumpsuit.inner_seam_length": "null",
		"metadata.jumpsuit.chest_size": "null",
		"metadata.jumpsuit.waist_size": "null",
		"metadata.jumpsuit.hip_size": "null",
		"metadata.jumpsuit.shoulder_width": "null",
		"metadata.jumpsuit.sleeve_length": "null",
		"metadata.jumpsuit.cuffs_size": "null",
		"metadata.jumpsuit.front_rise_length": "null",
		"metadata.jumpsuit.back_rise_length": "null",
		"metadata.jumpsuit.pants_waist_size": "null"
	}
}