{
	"dataset": {
		"dataset.id": 79401,
		"dataset.name": "01_sou_015881_079401_front_02top_02t-shirt_man",
		"dataset.image_path": "./008.의류 통합 데이터(3-1)/원천데이터/상품/상의/t-shirt/01_sou_015881_079401_front_02top_02t-shirt_man.jpg",
		"dataset.label_path": "./008.의류 통합 데이터(3-1)/라벨링데이터/상품/상의/t-shirt/01_sou_015881_079401_front_02top_02t-shirt_man.json",
		"dataset.category": 6,
		"dataset.type": 1,
		"dataset.width": 1920,
		"dataset.height": 1080,
		"dataset.file_size": 229477
	},
	"annotation": [
		{
			"annotation_type": "Polygon",
			"annotation_id": 182,
			"annotation_point_count": 68.0,
			"annotation_point": [
				1036.0,
				105.0,
				948.0,
				129.0,
				895.0,
				126.0,
				866.3000000000011,
				108.90000000000146,
				792.958984375,
				131.2138671875,
				784.5917001338657,
				132.6087684069571,
				771.3442659526972,
				136.09493529674,
				762.2802320392657,
				138.88386880856524,
				750.4272646140089,
				142.37003569834633,
				739.9687639446638,
				145.15896921017156,
				728.8130298973647,
				147.9479027219968,
				719.7489959839331,
				151.4340696117779,
				709.290495314588,
				157.01193663542654,
				700.2264614011565,
				162.589803659077,
				691.1624274877249,
				168.16767068272748,
				680.0066934404258,
				174.4427710843338,
				669.5481927710807,
				179.32340473002841,
				659.7869254796933,
				184.2040383757212,
				649.32842481035,
				189.78190539937168,
				638.869924141005,
				192.57083891119692,
				628.4114234716617,
				192.57083891119692,
				615.861222668449,
				196.75423917893568,
				607.4944221329733,
				203.72657295849785,
				598.4303882195418,
				209.30443998214832,
				557.2936189201209,
				232.31314145470424,
				475.02008032128106,
				271.3582106202557,
				406.7000000000007,
				308.3000000000011,
				209.0,
				415.0,
				121.0,
				474.0,
				74.0,
				531.0,
				33.0,
				557.0,
				33.0,
				578.0,
				57.0,
				605.0,
				62.0,
				638.0,
				80.0,
				650.0,
				139.0,
				620.0,
				225.10000000000036,
				624.2000000000007,
				382.8000000000011,
				567.1000000000004,
				557.1000000000004,
				509.10000000000036,
				597.8000000000011,
				481.7000000000007,
				614.4000000000015,
				474.40000000000146,
				608.0,
				715.0,
				649.0,
				930.0,
				690.0,
				921.0,
				924.0,
				915.0,
				1065.0,
				918.0,
				1188.0,
				930.0,
				1223.0,
				939.0,
				1235.0,
				936.0,
				1264.0,
				834.0,
				1284.1000000000004,
				695.4000000000015,
				1276.0,
				507.0,
				1346.0,
				525.0,
				1452.0,
				572.0,
				1598.0,
				623.0,
				1669.0,
				638.0,
				1733.0,
				641.0,
				1786.0,
				665.0,
				1814.800000000001,
				665.0,
				1823.1000000000004,
				620.0,
				1845.0,
				584.0,
				1845.0,
				572.0,
				1799.7000000000007,
				540.3000000000011,
				1757.0,
				492.0,
				1569.0,
				394.0,
				1381.0,
				272.0,
				1165.0,
				149.0,
				1082.0,
				126.0
			]
		}
	],
	"metadata.model": {
		"metadata.model.gender": "MALE",
		"metadata.model.age": "20대",
		"metadata.model.job": "not employed",
		"metadata.model.type": "front",
		"metadata.model.usually_size": "XL",
		"metadata.model.body_height": "185",
		"metadata.model.waist_height": "110",
		"metadata.model.chest_size_male": "105.0",
		"metadata.model.breast_size_female": "null",
		"metadata.model.waist_size": "80",
		"metadata.model.hip_seize": "99",
		"metadata.model.back_length": "50",
		"metadata.model.shoulders_width": "50",
		"metadata.model.arm_length": "62",
		"metadata.model.weight": "85"
	},
	"metadata.clothes": {
		"metadata.clothes.type": "02top_02t-shirt",
		"metadata.clothes.season": "spring&fall",
		"metadata.clothes.fiber_composition": "Cotton",
		"metadata.clothes.elasticity": "none",
		"metadata.clothes.transparency": "none at all",
		"metadata.clothes.isfleece": "fleece_none",
		"metadata.clothes.color": "White",
		"metadata.clothes.washing_method": "Washing30",
		"metadata.clothes.bleach": "Do not chlorine bleach",
		"metadata.clothes.ironing": "Ironing 140~160℃",
		"metadata.clothes.drycleaning": "DRYCLEAN",
		"metadata.clothes.wringing": "none",
		"metadata.clothes.drying": "Line dry in shade",
		"metadata.clothes.top_length_type": "long",
		"metadata.clothes.sleeve_length_type": "long sleeves",
		"metadata.clothes.topneck_color_design": "round neck",
		"metadata.clothes.topsleeve_design": "ribbed sleeve",
		"metadata.clothes.pants_silhouette": "null",
		"metadata.clothes.skirt_design": "null",
		"metadata.top.front_length": "72.0",
		"metadata.top.chest_size": "116.0",
		"metadata.top.waist_size": "114.0",
		"metadata.top.hem_size": "104.0",
		"metadata.top.shoulder_width": "55.0",
		"metadata.top.sleeve_length": "61.0",
		"metadata.top.sleeve_cuff_size": "34.0",
		"metadata.pants.pants_length": "null",
		"metadata.pants.waist_size": "null",
		"metadata.pants.hip_size": "null",
		"metadata.pants.front_rise_length": "null",
		"metadata.pants.back_rise_length": "null",
		"metadata.pants.inner_seam_length": "null",
		"metadata.pants.pants_waist_size": "null",
		"metadata.skirt.length": "null",
		"metadata.skirt.waist_size": "null",
		"metadata.skirt.hip_size": "null",
		"metadata.skirt.hem_size": "null",
		"metadata.dress.front_length": "null",
		"metadata.dress.chest_size": "null",
		"metadata.dress.waist_size": "null",
		"metadata.dress.hip_size": "null",
		"metadata.dress.hem_size": "null",
		"metadata.dress.shoulder_width": "null",
		"metadata.dress.sleeve_length": "null",
		"metadata.dress.cuff_size": "null",
		"metadata.jumpsuit.front_length": "null",
		"metadata.jumpsuit.inner_seam_length": "null",
		"metadata.jumpsuit.chest_size": "null",
		"metadata.jumpsuit.waist_size": "null",
		"metadata.jumpsuit.hip_size": "null",
		"metadata.jumpsuit.shoulder_width": "null",
		"metadata.jumpsuit.sleeve_length": "null",
		"metadata.jumpsuit.cuffs_size": "null",
		"metadata.jumpsuit.front_rise_length": "null",
		"metadata.jumpsuit.back_rise_length": "null",
		"metadata.jumpsuit.pants_waist_size": "null"
	}
}