{
	"dataset": {
		"dataset.id": 90900,
		"dataset.name": "01_sou_018180_090900_wear_02top_02t-shirt_woman",
		"dataset.image_path": "./008.의류 통합 데이터(3-1)/원천데이터/상품/상의/t-shirt/01_sou_018180_090900_wear_02top_02t-shirt_woman.jpg",
		"dataset.label_path": "./008.의류 통합 데이터(3-1)/라벨링데이터/상품/상의/t-shirt/01_sou_018180_090900_wear_02top_02t-shirt_woman.json",
		"dataset.category": 6,
		"dataset.type": 1,
		"dataset.width": 607,
		"dataset.height": 1080,
		"dataset.file_size": 47950
	},
	"annotation": [
		{
			"annotation_type": "Polygon",
			"annotation_id": 92,
			"annotation_point_count": 64.0,
			"annotation_point": [
				337.3000000000011,
				230.40000000000146,
				302.0,
				258.0,
				280.0,
				271.0,
				273.0,
				272.0,
				260.0,
				286.0,
				242.0,
				299.0,
				236.0,
				310.0,
				221.0,
				351.0,
				218.0,
				366.0,
				219.0,
				401.0,
				213.0,
				422.0,
				221.0,
				431.0,
				224.0,
				514.0,
				222.0,
				591.0,
				229.0,
				596.0,
				245.0,
				597.0,
				258.0,
				601.0,
				277.0,
				601.0,
				295.0,
				604.0,
				365.0,
				603.0,
				368.6964353431922,
				599.9606560485408,
				369.28896473265013,
				591.0727152066756,
				369.28896473265013,
				582.1847743648068,
				370.474023511566,
				573.2968335229416,
				372.25161167993974,
				564.4088926810764,
				374.0291998483117,
				555.5209518392112,
				378.17690557451533,
				547.2255403868039,
				380.547023132347,
				538.3375995449387,
				381.73208191126287,
				529.4496587030699,
				381.73208191126287,
				519.9691884717467,
				381.13955252180494,
				511.67377701933947,
				380.547023132347,
				508.71113007204985,
				379.9544937428891,
				499.82318923018465,
				379.3619643534312,
				489.7501896094036,
				376.9918467956013,
				479.67718998862256,
				374.0291998483117,
				470.19671975729943,
				371.6590822904818,
				461.30877891543423,
				368.6964353431922,
				451.8283086841111,
				366.91884717482026,
				443.532897231702,
				363.95620022753064,
				434.6449563898368,
				360.4010238907849,
				425.1644861585137,
				356.8458475540392,
				416.27654531664666,
				354.4757299962075,
				407.9811338642394,
				354.4757299962075,
				397.90813424345833,
				359.2159651118691,
				390.20525218050716,
				364.54872961698857,
				382.5023701175578,
				371.6590822904818,
				375.39201744406455,
				378.17690557451533,
				368.2816647705731,
				384.69472885855066,
				362.3563708759957,
				392.39761092150184,
				367.09660599165727,
				394.1751990898738,
				375.9845468335225,
				394.7677284793317,
				386.0575464543035,
				396.544921875,
				393.7607421875,
				404.0,
				387.0,
				406.0,
				382.0,
				406.0,
				375.0,
				413.0,
				359.0,
				394.0,
				317.0,
				391.0,
				304.0,
				391.0,
				292.0,
				387.0,
				276.0,
				376.0,
				254.0,
				372.0,
				248.0,
				354.0,
				239.0
			]
		}
	],
	"metadata.model": {
		"metadata.model.gender": "FEMALE",
		"metadata.model.age": "30대",
		"metadata.model.job": "entertainment and sports",
		"metadata.model.type": "wear",
		"metadata.model.usually_size": "M",
		"metadata.model.body_height": "166",
		"metadata.model.waist_height": "99",
		"metadata.model.chest_size_male": "null",
		"metadata.model.breast_size_female": "83.0",
		"metadata.model.waist_size": "66",
		"metadata.model.hip_seize": "91",
		"metadata.model.back_length": "44",
		"metadata.model.shoulders_width": "45",
		"metadata.model.arm_length": "53",
		"metadata.model.weight": "52"
	},
	"metadata.clothes": {
		"metadata.clothes.type": "02top_02t-shirt",
		"metadata.clothes.season": "summer",
		"metadata.clothes.fiber_composition": "Cotton",
		"metadata.clothes.elasticity": "contain little",
		"metadata.clothes.transparency": "none at all",
		"metadata.clothes.isfleece": "fleece_none",
		"metadata.clothes.color": "Black",
		"metadata.clothes.washing_method": "none",
		"metadata.clothes.bleach": "none",
		"metadata.clothes.ironing": "none",
		"metadata.clothes.drycleaning": "none",
		"metadata.clothes.wringing": "none",
		"metadata.clothes.drying": "none",
		"metadata.clothes.top_length_type": "normal",
		"metadata.clothes.sleeve_length_type": "short sleeves",
		"metadata.clothes.topneck_color_design": "round neck",
		"metadata.clothes.topsleeve_design": "basic sleeve",
		"metadata.clothes.pants_silhouette": "null",
		"metadata.clothes.skirt_design": "null",
		"metadata.top.front_length": "67.0",
		"metadata.top.chest_size": "108.0",
		"metadata.top.waist_size": "106.0",
		"metadata.top.hem_size": "106.0",
		"metadata.top.shoulder_width": "48.0",
		"metadata.top.sleeve_length": "22.0",
		"metadata.top.sleeve_cuff_size": "30.0",
		"metadata.pants.pants_length": "null",
		"metadata.pants.waist_size": "null",
		"metadata.pants.hip_size": "null",
		"metadata.pants.front_rise_length": "null",
		"metadata.pants.back_rise_length": "null",
		"metadata.pants.inner_seam_length": "null",
		"metadata.pants.pants_waist_size": "null",
		"metadata.skirt.length": "null",
		"metadata.skirt.waist_size": "null",
		"metadata.skirt.hip_size": "null",
		"metadata.skirt.hem_size": "null",
		"metadata.dress.front_length": "null",
		"metadata.dress.chest_size": "null",
		"metadata.dress.waist_size": "null",
		"metadata.dress.hip_size": "null",
		"metadata.dress.hem_size": "null",
		"metadata.dress.shoulder_width": "null",
		"metadata.dress.sleeve_length": "null",
		"metadata.dress.cuff_size": "null",
		"metadata.jumpsuit.front_length": "null",
		"metadata.jumpsuit.inner_seam_length": "null",
		"metadata.jumpsuit.chest_size": "null",
		"metadata.jumpsuit.waist_size": "null",
		"metadata.jumpsuit.hip_size": "null",
		"metadata.jumpsuit.shoulder_width": "null",
		"metadata.jumpsuit.sleeve_length": "null",
		"metadata.jumpsuit.cuffs_size": "null",
		"metadata.jumpsuit.front_rise_length": "null",
		"metadata.jumpsuit.back_rise_length": "null",
		"metadata.jumpsuit.pants_waist_size": "null"
	}
}