{
	"dataset": {
		"dataset.id": 12545,
		"dataset.name": "01_sou_002509_012545_wear_02top_02t-shirt_man",
		"dataset.image_path": "./008.의류 통합 데이터(3-1)/원천데이터/상품/상의/t-shirt/01_sou_002509_012545_wear_02top_02t-shirt_man.jpg",
		"dataset.label_path": "./008.의류 통합 데이터(3-1)/라벨링데이터/상품/상의/t-shirt/01_sou_002509_012545_wear_02top_02t-shirt_man.json",
		"dataset.category": 6,
		"dataset.type": 1,
		"dataset.width": 810,
		"dataset.height": 1080,
		"dataset.file_size": 55598
	},
	"annotation": [
		{
			"annotation_type": "Polygon",
			"annotation_id": 281,
			"annotation_point_count": 68.0,
			"annotation_point": [
				536.0,
				348.0,
				521.0,
				335.0,
				509.0,
				328.0,
				479.2604284103709,
				321.4611048478,
				485.2000000000007,
				333.10000000000036,
				479.10000000000036,
				348.3000000000011,
				465.86696730552285,
				349.4656144306646,
				447.10000000000036,
				343.2000000000007,
				430.55693348365276,
				333.63697857948137,
				417.1634723788047,
				323.896279594137,
				403.76953125,
				310.5029296875,
				403.76953125,
				310.5029296875,
				392.0,
				313.0,
				380.0,
				320.0,
				367.0,
				323.0,
				349.0,
				334.0,
				342.0,
				344.0,
				326.0,
				388.0,
				306.0,
				438.0,
				319.0,
				449.0,
				323.60000000000036,
				443.40000000000146,
				330.7147688838777,
				444.43742953776746,
				363.5896279594126,
				455.3957158962785,
				366.0,
				443.0,
				371.0,
				448.0,
				373.6044921875,
				467.66796875,
				373.6044921875,
				467.66796875,
				373.6045101842865,
				473.22462010992604,
				374.61485612673823,
				481.30738764953094,
				375.1200290979632,
				490.90567410281255,
				375.1200290979632,
				498.98844164241746,
				374.10968315551327,
				506.5660362107992,
				373.0993372130615,
				514.6488037504041,
				372.59416424183655,
				522.731571290009,
				372.0889912706116,
				532.3298577432906,
				372.0889912706116,
				541.4229712253473,
				372.0889912706116,
				549.0005657937272,
				372.0889912706116,
				558.0936792757839,
				371.07864532815984,
				567.1867927578405,
				370.0682993857099,
				574.2592143549955,
				369.05795344325816,
				581.8368089233754,
				368.0476075008082,
				589.9195764629803,
				368.0476075008082,
				598.507516973812,
				370.5734723569349,
				607.0954574846419,
				376.6355480116399,
				609.1161493695436,
				381.1821047526664,
				571.7333494988688,
				390.27521823472307,
				611.1368412544452,
				397.34763983187804,
				609.1161493695436,
				403.4097154865831,
				607.6006304558687,
				413.0080019398647,
				605.579938570967,
				421.59594245069457,
				605.074765599742,
				431.1942289039762,
				605.074765599742,
				440.28734238603283,
				604.0644196572903,
				448.90000000000146,
				604.1000000000004,
				456.45287746524446,
				604.5695926285152,
				469.10000000000036,
				606.1000000000004,
				475.6494503718077,
				604.5695926285152,
				505.0,
				600.0,
				529.0,
				588.0,
				527.0,
				559.0,
				528.0,
				506.0,
				525.0,
				493.0,
				525.0,
				461.0,
				527.0,
				458.0,
				563.6000000000004,
				447.0,
				557.0,
				429.0,
				545.0,
				392.0,
				543.0,
				376.0
			]
		}
	],
	"metadata.model": {
		"metadata.model.gender": "MALE",
		"metadata.model.age": "50대 이상",
		"metadata.model.job": "service job",
		"metadata.model.type": "wear",
		"metadata.model.usually_size": "M",
		"metadata.model.body_height": "173",
		"metadata.model.waist_height": "94",
		"metadata.model.chest_size_male": "104.0",
		"metadata.model.breast_size_female": "null",
		"metadata.model.waist_size": "90",
		"metadata.model.hip_seize": "96",
		"metadata.model.back_length": "52",
		"metadata.model.shoulders_width": "45",
		"metadata.model.arm_length": "57",
		"metadata.model.weight": "70"
	},
	"metadata.clothes": {
		"metadata.clothes.type": "02top_02t-shirt",
		"metadata.clothes.season": "summer",
		"metadata.clothes.fiber_composition": "Cotton",
		"metadata.clothes.elasticity": "contain little",
		"metadata.clothes.transparency": "none",
		"metadata.clothes.isfleece": "fleece_none",
		"metadata.clothes.color": "Gray",
		"metadata.clothes.washing_method": "none",
		"metadata.clothes.bleach": "none",
		"metadata.clothes.ironing": "none",
		"metadata.clothes.drycleaning": "none",
		"metadata.clothes.wringing": "none",
		"metadata.clothes.drying": "none",
		"metadata.clothes.top_length_type": "normal",
		"metadata.clothes.sleeve_length_type": "short sleeves",
		"metadata.clothes.topneck_color_design": "round neck",
		"metadata.clothes.topsleeve_design": "basic sleeve",
		"metadata.clothes.pants_silhouette": "null",
		"metadata.clothes.skirt_design": "null",
		"metadata.top.front_length": "63.0",
		"metadata.top.chest_size": "100.0",
		"metadata.top.waist_size": "100.0",
		"metadata.top.hem_size": "102.0",
		"metadata.top.shoulder_width": "44.0",
		"metadata.top.sleeve_length": "23.0",
		"metadata.top.sleeve_cuff_size": "30.0",
		"metadata.pants.pants_length": "null",
		"metadata.pants.waist_size": "null",
		"metadata.pants.hip_size": "null",
		"metadata.pants.front_rise_length": "null",
		"metadata.pants.back_rise_length": "null",
		"metadata.pants.inner_seam_length": "null",
		"metadata.pants.pants_waist_size": "null",
		"metadata.skirt.length": "null",
		"metadata.skirt.waist_size": "null",
		"metadata.skirt.hip_size": "null",
		"metadata.skirt.hem_size": "null",
		"metadata.dress.front_length": "null",
		"metadata.dress.chest_size": "null",
		"metadata.dress.waist_size": "null",
		"metadata.dress.hip_size": "null",
		"metadata.dress.hem_size": "null",
		"metadata.dress.shoulder_width": "null",
		"metadata.dress.sleeve_length": "null",
		"metadata.dress.cuff_size": "null",
		"metadata.jumpsuit.front_length": "null",
		"metadata.jumpsuit.inner_seam_length": "null",
		"metadata.jumpsuit.chest_size": "null",
		"metadata.jumpsuit.waist_size": "null",
		"metadata.jumpsuit.hip_size": "null",
		"metadata.jumpsuit.shoulder_width": "null",
		"metadata.jumpsuit.sleeve_length": "null",
		"metadata.jumpsuit.cuffs_size": "null",
		"metadata.jumpsuit.front_rise_length": "null",
		"metadata.jumpsuit.back_rise_length": "null",
		"metadata.jumpsuit.pants_waist_size": "null"
	}
}